tft_torch/__init__.py
tft_torch/base_blocks.py
tft_torch/loss.py
tft_torch/tft.py
tft_torch/visualize.py
tft_torch-0.0.6.dist-info/AUTHORS.rst
tft_torch-0.0.6.dist-info/LICENSE
tft_torch-0.0.6.dist-info/METADATA
tft_torch-0.0.6.dist-info/WHEEL
tft_torch-0.0.6.dist-info/top_level.txt
tft_torch-0.0.6.dist-info/RECORD
