Metadata-Version: 2.1
Name: tft-torch
Version: 0.0.6
Summary: A Python library that implements ״Temporal Fusion Transformers for Interpretable Multi-horizon Time Series Forecasting״
Home-page: https://github.com/PlaytikaOSS/tft-torch
Author: Dvir Ben Or
Author-email: dvirb@playtika.com
Project-URL: Bug Tracker, https://github.com/PlaytikaOSS/tft-torch/issues
Classifier: Programming Language :: Python :: 3
Classifier: License :: OSI Approved :: MIT License
Classifier: Operating System :: OS Independent
Requires-Python: >=3.7
License-File: LICENSE
License-File: AUTHORS.rst
Requires-Dist: omegaconf
Requires-Dist: torch (>=1.6.0)
Requires-Dist: numpy
Requires-Dist: pandas
Requires-Dist: scikit-learn
Requires-Dist: matplotlib
Provides-Extra: develop
Requires-Dist: flake8 (>=3.9.2) ; extra == 'develop'
Requires-Dist: ipython (>=7.23.1) ; extra == 'develop'
Requires-Dist: nbsphinx (>=0.8.4) ; extra == 'develop'
Requires-Dist: pandoc (>=1.0.2) ; extra == 'develop'
Requires-Dist: pre-commit (>=2.12.1) ; extra == 'develop'
Requires-Dist: pytest (>=6.2.4) ; extra == 'develop'
Requires-Dist: setuptools (>=52.0.0) ; extra == 'develop'
Requires-Dist: sphinx (>=4.0.0) ; extra == 'develop'
Requires-Dist: sphinx-rtd-theme (>=0.5.2) ; extra == 'develop'
Requires-Dist: wheel (>=0.36.2) ; extra == 'develop'
Requires-Dist: build ; extra == 'develop'
Requires-Dist: recommonmark ; extra == 'develop'
